foreach/__init__.py
foreach-0.4.0.dist-info/LICENSE
foreach-0.4.0.dist-info/METADATA
foreach-0.4.0.dist-info/WHEEL
foreach-0.4.0.dist-info/RECORD
