Metadata-Version: 2.1
Name: foreach
Version: 0.4.0
Summary: 
Author: Jaime Liew
Author-email: jaimeliew1@gmail.com
Requires-Python: >=3.7,<4.0
Classifier: Programming Language :: Python :: 3
Classifier: Programming Language :: Python :: 3.7
Classifier: Programming Language :: Python :: 3.8
Classifier: Programming Language :: Python :: 3.9
Classifier: Programming Language :: Python :: 3.10
Classifier: Programming Language :: Python :: 3.11
Requires-Dist: tqdm (>=4.66.1,<5.0.0)
